examples/EEG_AD_FTD/EEG_AD_FTD.py
examples/EEG_AD_FTD/figures/EEG_predictions.py
examples/LFP_developing_brain/LFP_developing_brain.py
examples/LFP_developing_brain/figures/LFP_predictions.py
examples/LFP_developing_brain/figures/emp_features.py
examples/simulation/Hagen_model/figures/SBI_results.py
examples/simulation/Hagen_model/figures/example_full_pipeline.py
examples/simulation/Hagen_model/figures/save_code_as_image.py
examples/simulation/Hagen_model/figures/sim_features.py
examples/simulation/Hagen_model/figures/sim_predictions.py
examples/simulation/Hagen_model/simulation/compute_features.py
examples/simulation/Hagen_model/simulation/example_model_simulation.py
examples/simulation/Hagen_model/simulation/preprocessing.py
examples/simulation/Hagen_model/simulation/sim_statistics.py
examples/simulation/Hagen_model/simulation/params/analysis_params.py
examples/simulation/Hagen_model/simulation/params/network_params.py
examples/simulation/Hagen_model/simulation/params/simulation_params.py
examples/simulation/Hagen_model/simulation/python/analysis.py
examples/simulation/Hagen_model/simulation/python/network.py
examples/simulation/Hagen_model/simulation/python/simulation.py
examples/simulation/Hagen_model/train/RepeatedKFold.py
ncpi/Analysis.py
ncpi/Features.py
ncpi/FieldPotential.py
ncpi/Inference.py
ncpi/Simulation.py
ncpi/__init__.py
ncpi/tools.py
ncpi-0.2.6.dist-info/licenses/LICENSE
ncpi-0.2.6.dist-info/METADATA
ncpi-0.2.6.dist-info/WHEEL
ncpi-0.2.6.dist-info/top_level.txt
ncpi-0.2.6.dist-info/RECORD
