Metadata-Version: 2.4
Name: ncpi
Version: 0.2.6
Summary: Neural circuit parameter inference using electrophysiological data
Author-email: necolab <pablomc@ugr.es>
License:                     GNU GENERAL PUBLIC LICENSE
Project-URL: repository, https://github.com/necolab-ugr/ncpi
Project-URL: documentation, https://necolab-ugr.github.io/ncpi
Keywords: biomarkers,parameter-inference,neural-circuits,electrophysiological-data,brain-simulation
Classifier: Intended Audience :: Developers
Classifier: Intended Audience :: Education
Classifier: Intended Audience :: Science/Research
Classifier: Topic :: Scientific/Engineering
Classifier: Natural Language :: English
Classifier: Operating System :: OS Independent
Classifier: Programming Language :: Python :: 3
Classifier: License :: OSI Approved :: MIT License
Requires-Python: >=3.10
License-File: LICENSE
Requires-Dist: scikit-learn==1.3.2
Requires-Dist: sbi==0.24.0
Requires-Dist: torch
Requires-Dist: pycatch22
Requires-Dist: fooof
Requires-Dist: numpy
Requires-Dist: pandas
Requires-Dist: scipy
Requires-Dist: matplotlib
Provides-Extra: simulation
Requires-Dist: lfpykernels; extra == "simulation"
Provides-Extra: utils
Requires-Dist: h5py; extra == "utils"
Requires-Dist: pathos; extra == "utils"
Requires-Dist: tqdm; extra == "utils"
Requires-Dist: requests; extra == "utils"
Provides-Extra: statistics
Requires-Dist: rpy2; extra == "statistics"
Provides-Extra: visualization
Requires-Dist: seaborn; extra == "visualization"
Requires-Dist: mne; extra == "visualization"
Requires-Dist: mpl_toolkits; extra == "visualization"
Provides-Extra: feats-hctsa
Requires-Dist: matlab.engine; extra == "feats-hctsa"
Requires-Dist: h5py; extra == "feats-hctsa"
Provides-Extra: feats-fei-dfa
Requires-Dist: PyAstronomy; extra == "feats-fei-dfa"
Dynamic: license-file
